Metadata-Version: 2.1
Name: archive-manager
Version: 0.1.4
Summary: Manage backup archive files
Home-page: https://github.com/ccollicutt/archive-manager
Author: Curtis Collicutt
Author-email: curtis@serverascode.com
License: Apache License, Version 2.0
Download-URL: https://github.com/ccollicutt/archive-manager/archive/v0.1.4.tar.gz
Keywords: backup,file manager,archive,archive manager
Platform: UNKNOWN
Requires-Python: >=2.7, !=3.*
